apunim/__init__.py
apunim/_list_dict.py
apunim-1.0.1.dist-info/METADATA
apunim-1.0.1.dist-info/WHEEL
apunim-1.0.1.dist-info/licenses/LICENSE
apunim-1.0.1.dist-info/RECORD
